dora_openai_server/__init__.py
dora_openai_server/main.py
dora_openai_server-0.4.1.dist-info/METADATA
dora_openai_server-0.4.1.dist-info/WHEEL
dora_openai_server-0.4.1.dist-info/entry_points.txt
dora_openai_server-0.4.1.dist-info/top_level.txt
dora_openai_server-0.4.1.dist-info/RECORD
