Metadata-Version: 2.4
Name: dora-openai-server
Version: 0.4.1
Summary: Dora OpenAI API Server
Author-email: Haixuan Xavier Tao <tao.xavier@outlook.com>, Enzo Le Van <dev@enzo-le-van.fr>
License: MIT
Requires-Python: >=3.8
Requires-Dist: dora-rs>=0.3.9
Requires-Dist: numpy<2.0.0
Requires-Dist: pyarrow>=5.0.0
Requires-Dist: fastapi>=0.115
Requires-Dist: asyncio>=3.4
Requires-Dist: uvicorn>=0.31
Requires-Dist: pydantic>=2.9
